numpickle/__init__.py
numpickle/main.py
numpickle-0.1.3.post6.dist-info/WHEEL
numpickle-0.1.3.post6.dist-info/METADATA
numpickle-0.1.3.post6.dist-info/RECORD
