Metadata-Version: 2.1
Name: numpickle
Version: 0.1.3.post6
Summary: Faster loading of pandas data frames by saving them as numpy arrays and pickling their meta info (row+column names, column dtype info).
Home-page: https://github.com/gwangjinkim/numpickle
License: MIT
Keywords: Excel,Pandas,data frame,I/O
Author: Gwang-Jin Kim
Author-email: gwang.jin.kim.phd@gmail.com
Maintainer: Gwang-Jin Kim
Maintainer-email: gwang.jin.kim.phd@gmail.com
Requires-Python: >=3.5.0,<4.0.0
Classifier: License :: OSI Approved :: MIT License
Classifier: Programming Language :: Python :: 3
Classifier: Programming Language :: Python :: 3.5
Classifier: Programming Language :: Python :: 3.6
Classifier: Programming Language :: Python :: 3.7
Classifier: Programming Language :: Python :: 3.8
Classifier: Programming Language :: Python :: 3.9
Requires-Dist: numpy (>=1.18.2,<2.0.0)
Requires-Dist: pandas (>=0.24.2,<0.25.0)
Project-URL: Documentation, https://gwang-jin-kim.medium.com/faster-loading-and-saving-of-pandas-data-frames-using-numpickle-numpy-and-pickle-d15870519529
Project-URL: Repository, https://github.com/gwangjinkim/numpickle
